rhjira/__init__.py
rhjira/_version.py
rhjira/cli.py
rhjira/clone.py
rhjira/comment.py
rhjira/create.py
rhjira/dump.py
rhjira/edit.py
rhjira/hierarchy.py
rhjira/info.py
rhjira/list.py
rhjira/login.py
rhjira/py.typed
rhjira/show.py
rhjira/util.py
rhjira-3.1.0.dist-info/licenses/LICENSE
rhjira-3.1.0.dist-info/METADATA
rhjira-3.1.0.dist-info/WHEEL
rhjira-3.1.0.dist-info/entry_points.txt
rhjira-3.1.0.dist-info/top_level.txt
rhjira-3.1.0.dist-info/RECORD
