Metadata-Version: 2.4
Name: rhjira
Version: 3.1.0
Summary: CLI for Red Hat Jira (https://issues.redhat.com)
Author-email: Prarit Bhargava <prarit@redhat.com>
Maintainer-email: Prarit Bhargava <prarit@redhat.com>
License-Expression: GPL-2.0-or-later
Project-URL: Homepage, https://gitlab.com/prarit/rhjira-python
Keywords: redhat,jira
Requires-Python: >=3.11
License-File: LICENSE
Requires-Dist: keyring
Requires-Dist: jira>=3.2.0
Requires-Dist: requests>=2.0.0
Requires-Dist: pillow>=8.0.0
Requires-Dist: tabulate
Provides-Extra: dev
Requires-Dist: ruff>=0.2.0; extra == "dev"
Requires-Dist: mypy>=1.8.0; extra == "dev"
Requires-Dist: types-requests; extra == "dev"
Requires-Dist: types-tabulate; extra == "dev"
Requires-Dist: pytest; extra == "dev"
Dynamic: license-file
